MANIFEST.in
README.textile
setup.py
continuous_services/__init__.py
continuous_services/service.py
continuous_services.egg-info/PKG-INFO
continuous_services.egg-info/SOURCES.txt
continuous_services.egg-info/dependency_links.txt
continuous_services.egg-info/requires.txt
continuous_services.egg-info/top_level.txt
continuous_services/services/__init__.py
continuous_services/services/email/__init__.py
continuous_services/services/email/form.py
continuous_services/services/email/service.py
continuous_services/services/jabber/__init__.py
continuous_services/services/jabber/form.py
continuous_services/services/jabber/service.py
continuous_services/services/jabber/utilities.py
continuous_services/services/skeleton/__init__.py
continuous_services/services/skeleton/form.py
continuous_services/services/skeleton/service.py