Metadata-Version: 1.0
Name: continuous-services
Version: 0.1.1
Summary: Official continuous.io services integration - Access these services in your project's admin screen
Home-page: https://github.com/continuous/continuous-services
Author: Adam Charnock
Author-email: adam@continuous.io
License: Dual license: Apache Software License, GPL v3
Platform: UNKNOWN
Classifier: Development Status :: 4 - Beta
Classifier: Environment :: Plugins
Classifier: Intended Audience :: Developers
Classifier: Natural Language :: English
Classifier: Programming Language :: Python :: 2.6
Classifier: Topic :: Software Development :: Quality Assurance
Classifier: Topic :: Software Development :: Testing
